nonebot_plugin_yiyan/README.md
nonebot_plugin_yiyan/__init__.py
nonebot_plugin_yiyan/utils/__init__.py
nonebot_plugin_yiyan/utils/browser.py
nonebot_plugin_yiyan/utils/data_utils.py
nonebot_plugin_yiyan/utils/game_utils.py
nonebot_plugin_yiyan/utils/http_utils.py
nonebot_plugin_yiyan/utils/image_template.py
nonebot_plugin_yiyan/utils/image_utils.py
nonebot_plugin_yiyan/utils/langconv.py
nonebot_plugin_yiyan/utils/message_builder.py
nonebot_plugin_yiyan/utils/text_utils.py
nonebot_plugin_yiyan/utils/typing.py
nonebot_plugin_yiyan/utils/user_agent.py
nonebot_plugin_yiyan/utils/utils.py
nonebot_plugin_yiyan/utils/zh_wiki.py
nonebot_plugin_yiyan/utils/decorator/__init__.py
nonebot_plugin_yiyan/utils/decorator/shop.py
nonebot_plugin_yiyan/utils/depends/__init__.py
nonebot_plugin_yiyan/utils/manager/__init__.py
nonebot_plugin_yiyan/utils/manager/admin_manager.py
nonebot_plugin_yiyan/utils/manager/configs_manager.py
nonebot_plugin_yiyan/utils/manager/data_class.py
nonebot_plugin_yiyan/utils/manager/group_manager.py
nonebot_plugin_yiyan/utils/manager/models.py
nonebot_plugin_yiyan/utils/manager/none_plugin_count_manager.py
nonebot_plugin_yiyan/utils/manager/plugin_data_manager.py
nonebot_plugin_yiyan/utils/manager/plugins2block_manager.py
nonebot_plugin_yiyan/utils/manager/plugins2cd_manager.py
nonebot_plugin_yiyan/utils/manager/plugins2count_manager.py
nonebot_plugin_yiyan/utils/manager/plugins2settings_manager.py
nonebot_plugin_yiyan/utils/manager/plugins_manager.py
nonebot_plugin_yiyan/utils/manager/requests_manager.py
nonebot_plugin_yiyan/utils/manager/resources_manager.py
nonebot_plugin_yiyan/utils/manager/withdraw_message_manager.py
nonebot_plugin_yiyan/utils/models/__init__.py
nonebot_plugin_yiyan-1.1.5.dist-info/METADATA
nonebot_plugin_yiyan-1.1.5.dist-info/WHEEL
nonebot_plugin_yiyan-1.1.5.dist-info/top_level.txt
nonebot_plugin_yiyan-1.1.5.dist-info/RECORD
