Metadata-Version: 2.1
Name: nonebot-plugin-yiyan
Version: 1.1.5
Summary: Nonebot文心一言对话平台
Home-page: https://github.com/barryblueice/nonebot-plugin-yiyan
Author: barryblueice
Author-email: barryblueice@outlook.com
Maintainer: barryblueice
Maintainer-email: barryblueice@outlook.com
Requires-Python: >=3.8,<4.0
Requires-Dist: nonebot2
Requires-Dist: nonebot-adapter-onebot
Requires-Dist: nonebot-plugin-apscheduler
Requires-Dist: requests
